{
  "medium_id": "dsmz_944",
  "medium_name": "Solution A:",
  "source": "dsmz",
  "composition": [
    {
      "name": "Solution A:",
      "concentration": 0.41,
      "unit": "g",
      "extraction_method": "pdf_tabular_parsing"
    },
    {
      "name": "KH2PO4",
      "concentration": 0.53,
      "unit": "g",
      "extraction_method": "pdf_tabular_parsing"
    },
    {
      "name": "Na2HPO4",
      "concentration": 1.06,
      "unit": "g",
      "extraction_method": "pdf_tabular_parsing"
    },
    {
      "name": "NaClO3",
      "concentration": 2.72,
      "unit": "g",
      "extraction_method": "pdf_tabular_parsing"
    },
    {
      "name": "Na-Acetate x 3 H2O",
      "concentration": 0.5,
      "unit": "mg",
      "extraction_method": "pdf_tabular_parsing"
    },
    {
      "name": "Trace element solution SL-10",
      "concentration": 1.0,
      "unit": "ml",
      "extraction_method": "pdf_tabular_parsing"
    },
    {
      "name": "Selenite-tungstate-molybdate solution",
      "concentration": 10.0,
      "unit": "ml",
      "extraction_method": "pdf_tabular_parsing"
    },
    {
      "name": "Solution B:",
      "concentration": 900.0,
      "unit": "ml",
      "extraction_method": "pdf_tabular_parsing"
    },
    {
      "name": "CaCl2",
      "concentration": 0.11,
      "unit": "g",
      "extraction_method": "pdf_tabular_parsing"
    },
    {
      "name": "MgCl2",
      "concentration": 0.1,
      "unit": "g",
      "extraction_method": "pdf_tabular_parsing"
    },
    {
      "name": "Solution C:",
      "concentration": 50.0,
      "unit": "ml",
      "extraction_method": "pdf_tabular_parsing"
    },
    {
      "name": "NH4HCO3",
      "concentration": 0.44,
      "unit": "g",
      "extraction_method": "pdf_tabular_parsing"
    },
    {
      "name": "NaHCO3",
      "concentration": 3.73,
      "unit": "g",
      "extraction_method": "pdf_tabular_parsing"
    },
    {
      "name": "Na2S x 9 H2O",
      "concentration": 0.5,
      "unit": "g",
      "extraction_method": "pdf_tabular_parsing"
    }
  ],
  "preparation_instructions": "",
  "extraction_method": "pdf_text_parsing"
}