{
  "medium_id": "dsmz_593",
  "medium_name": "NaCl",
  "source": "dsmz",
  "composition": [
    {
      "name": "NaCl",
      "concentration": 81.0,
      "unit": "g",
      "extraction_method": "pdf_tabular_parsing"
    },
    {
      "name": "MgCl2",
      "concentration": 7.0,
      "unit": "g",
      "extraction_method": "pdf_tabular_parsing"
    },
    {
      "name": "MgSO4",
      "concentration": 9.6,
      "unit": "g",
      "extraction_method": "pdf_tabular_parsing"
    },
    {
      "name": "CaCl2",
      "concentration": 0.36,
      "unit": "g",
      "extraction_method": "pdf_tabular_parsing"
    },
    {
      "name": "KCl",
      "concentration": 2.0,
      "unit": "g",
      "extraction_method": "pdf_tabular_parsing"
    },
    {
      "name": "NaHCO3",
      "concentration": 0.06,
      "unit": "g",
      "extraction_method": "pdf_tabular_parsing"
    },
    {
      "name": "NaBr",
      "concentration": 0.026,
      "unit": "g",
      "extraction_method": "pdf_tabular_parsing"
    },
    {
      "name": "Proteose peptone no. 3 (Difco)",
      "concentration": 5.0,
      "unit": "g",
      "extraction_method": "pdf_tabular_parsing"
    },
    {
      "name": "Yeast extract (Difco)",
      "concentration": 10.0,
      "unit": "g",
      "extraction_method": "pdf_tabular_parsing"
    },
    {
      "name": "Glucose",
      "concentration": 1.0,
      "unit": "g",
      "extraction_method": "pdf_tabular_parsing"
    }
  ],
  "preparation_instructions": "",
  "extraction_method": "pdf_text_parsing"
}