{
  "medium_id": "dsmz_1212",
  "medium_name": "Medium dsmz_1212",
  "source": "dsmz",
  "composition": [
    {
      "name": "NH4Cl",
      "concentration": 0.5,
      "unit": "g",
      "extraction_method": "pdf_tabular_parsing"
    },
    {
      "name": "KH2PO4",
      "concentration": 0.5,
      "unit": "g",
      "extraction_method": "pdf_tabular_parsing"
    },
    {
      "name": "NaCl",
      "concentration": 25.0,
      "unit": "g",
      "extraction_method": "pdf_tabular_parsing"
    },
    {
      "name": "Na2SO4",
      "concentration": 0.5,
      "unit": "g",
      "extraction_method": "pdf_tabular_parsing"
    },
    {
      "name": "MgSO4 x 7 H2O",
      "concentration": 0.2,
      "unit": "g",
      "extraction_method": "pdf_tabular_parsing"
    },
    {
      "name": "KCl",
      "concentration": 0.5,
      "unit": "g",
      "extraction_method": "pdf_tabular_parsing"
    },
    {
      "name": "Yeast extract",
      "concentration": 1.0,
      "unit": "g",
      "extraction_method": "pdf_tabular_parsing"
    },
    {
      "name": "Peptone",
      "concentration": 1.0,
      "unit": "g",
      "extraction_method": "pdf_tabular_parsing"
    },
    {
      "name": "Sodium DL-lactate",
      "concentration": 1.0,
      "unit": "g",
      "extraction_method": "pdf_tabular_parsing"
    },
    {
      "name": "Vitamin B12",
      "concentration": 15.0,
      "unit": "g",
      "extraction_method": "pdf_tabular_parsing"
    },
    {
      "name": "Na2CO3",
      "concentration": 5.0,
      "unit": "g",
      "extraction_method": "pdf_tabular_parsing"
    },
    {
      "name": "NaHCO3",
      "concentration": 5.0,
      "unit": "ml",
      "extraction_method": "pdf_tabular_parsing"
    },
    {
      "name": "Trace element solution (see below)",
      "concentration": 1.0,
      "unit": "ml",
      "extraction_method": "pdf_tabular_parsing"
    }
  ],
  "preparation_instructions": "",
  "extraction_method": "pdf_text_parsing"
}