{
  "medium_id": "dsmz_8",
  "medium_name": "Glucose",
  "source": "dsmz",
  "composition": [
    {
      "name": "Glucose",
      "concentration": 5.0,
      "unit": "g",
      "extraction_method": "pdf_tabular_parsing"
    },
    {
      "name": "Peptone",
      "concentration": 5.0,
      "unit": "g",
      "extraction_method": "pdf_tabular_parsing"
    },
    {
      "name": "Yeast extract",
      "concentration": 5.0,
      "unit": "g",
      "extraction_method": "pdf_tabular_parsing"
    },
    {
      "name": "CaCO3",
      "concentration": 5.0,
      "unit": "g",
      "extraction_method": "pdf_tabular_parsing"
    },
    {
      "name": "Agar",
      "concentration": 15.0,
      "unit": "g",
      "extraction_method": "pdf_tabular_parsing"
    }
  ],
  "preparation_instructions": "",
  "extraction_method": "pdf_text_parsing"
}