{
  "medium_id": "dsmz_333",
  "medium_name": "NH4Cl",
  "source": "dsmz",
  "composition": [
    {
      "name": "NH4Cl",
      "concentration": 0.4,
      "unit": "g",
      "extraction_method": "pdf_tabular_parsing"
    },
    {
      "name": "MgSO4 x 7 H2O",
      "concentration": 0.8,
      "unit": "g",
      "extraction_method": "pdf_tabular_parsing"
    },
    {
      "name": "Trace element solution",
      "concentration": 10.0,
      "unit": "ml",
      "extraction_method": "pdf_tabular_parsing"
    },
    {
      "name": "KH2PO4",
      "concentration": 4.0,
      "unit": "g",
      "extraction_method": "pdf_tabular_parsing"
    },
    {
      "name": "K2HPO4",
      "concentration": 4.0,
      "unit": "g",
      "extraction_method": "pdf_tabular_parsing"
    },
    {
      "name": "K2S4O6",
      "concentration": 3.0,
      "unit": "g",
      "extraction_method": "pdf_tabular_parsing"
    },
    {
      "name": "Bromocresol purple (saturated aq. solution)",
      "concentration": 2.0,
      "unit": "ml",
      "extraction_method": "pdf_tabular_parsing"
    }
  ],
  "preparation_instructions": "",
  "extraction_method": "pdf_text_parsing"
}