{
  "medium_id": "dsmz_135",
  "medium_name": "Final pH: 7.5 - 8.0",
  "source": "dsmz",
  "composition": [
    {
      "name": "Final pH: 7.5 - 8.0",
      "concentration": 1.0,
      "unit": "g",
      "extraction_method": "pdf_tabular_parsing"
    },
    {
      "name": "Final volume: 1021 ml",
      "concentration": 0.33,
      "unit": "g",
      "extraction_method": "pdf_tabular_parsing"
    },
    {
      "name": "NH4Cl",
      "concentration": 0.45,
      "unit": "g",
      "extraction_method": "pdf_tabular_parsing"
    },
    {
      "name": "KH2PO4",
      "concentration": 0.1,
      "unit": "g",
      "extraction_method": "pdf_tabular_parsing"
    },
    {
      "name": "K2HPO4",
      "concentration": 20.0,
      "unit": "ml",
      "extraction_method": "pdf_tabular_parsing"
    },
    {
      "name": "MgSO4 x 7 H2O",
      "concentration": 2.0,
      "unit": "g",
      "extraction_method": "pdf_tabular_parsing"
    },
    {
      "name": "Modified Wolin's mineral solution",
      "concentration": 0.5,
      "unit": "ml",
      "extraction_method": "pdf_tabular_parsing"
    },
    {
      "name": "Yeast extract",
      "concentration": 10.0,
      "unit": "g",
      "extraction_method": "pdf_tabular_parsing"
    },
    {
      "name": "NaHCO3",
      "concentration": 10.0,
      "unit": "g",
      "extraction_method": "pdf_tabular_parsing"
    },
    {
      "name": "D-Fructose",
      "concentration": 1.0,
      "unit": "ml",
      "extraction_method": "pdf_tabular_parsing"
    },
    {
      "name": "Wolin's vitamin solution (10x)",
      "concentration": 0.5,
      "unit": "g",
      "extraction_method": "pdf_tabular_parsing"
    },
    {
      "name": "L-Cysteine HCl x H2O",
      "concentration": 0.5,
      "unit": "g",
      "extraction_method": "pdf_tabular_parsing"
    },
    {
      "name": "Na2S x 9 H2O",
      "concentration": 1000.0,
      "unit": "ml",
      "extraction_method": "pdf_tabular_parsing"
    }
  ],
  "preparation_instructions": "",
  "extraction_method": "pdf_text_parsing"
}