{
  "medium_id": "dsmz_388",
  "medium_name": "KH2PO4",
  "source": "dsmz",
  "composition": [
    {
      "name": "KH2PO4",
      "concentration": 1.5,
      "unit": "g",
      "extraction_method": "pdf_tabular_parsing"
    },
    {
      "name": "Na2HPO4 x 12 H2O",
      "concentration": 4.2,
      "unit": "g",
      "extraction_method": "pdf_tabular_parsing"
    },
    {
      "name": "NH4Cl",
      "concentration": 0.5,
      "unit": "g",
      "extraction_method": "pdf_tabular_parsing"
    },
    {
      "name": "MgCl2 x 6 H2O",
      "concentration": 0.38,
      "unit": "g",
      "extraction_method": "pdf_tabular_parsing"
    },
    {
      "name": "CaCl2 x 2 H2O",
      "concentration": 0.06,
      "unit": "g",
      "extraction_method": "pdf_tabular_parsing"
    },
    {
      "name": "Fe(NH4)2(SO4)2 x 6 H2O",
      "concentration": 0.04,
      "unit": "g",
      "extraction_method": "pdf_tabular_parsing"
    },
    {
      "name": "CoCl2 x 6 H2O (0.1% w/v)",
      "concentration": 2.9,
      "unit": "ml",
      "extraction_method": "pdf_tabular_parsing"
    },
    {
      "name": "Na2MoO4 x 2 H2O (0.1% w/v)",
      "concentration": 2.4,
      "unit": "ml",
      "extraction_method": "pdf_tabular_parsing"
    },
    {
      "name": "Na2SeO3 x 5 H2O (0.01% w/v)",
      "concentration": 1.7,
      "unit": "ml",
      "extraction_method": "pdf_tabular_parsing"
    },
    {
      "name": "MnCl2 x 4 H2O (0.1% w/v)",
      "concentration": 2.0,
      "unit": "ml",
      "extraction_method": "pdf_tabular_parsing"
    },
    {
      "name": "ZnSO4 (0.1% w/v)",
      "concentration": 2.8,
      "unit": "ml",
      "extraction_method": "pdf_tabular_parsing"
    },
    {
      "name": "Yeast extract",
      "concentration": 2.0,
      "unit": "g",
      "extraction_method": "pdf_tabular_parsing"
    },
    {
      "name": "Polypeptone",
      "concentration": 2.0,
      "unit": "g",
      "extraction_method": "pdf_tabular_parsing"
    },
    {
      "name": "Starch (soluble)",
      "concentration": 5.0,
      "unit": "g",
      "extraction_method": "pdf_tabular_parsing"
    },
    {
      "name": "Na2CO3",
      "concentration": 0.5,
      "unit": "ml",
      "extraction_method": "pdf_tabular_parsing"
    },
    {
      "name": "L-Cysteine HCl x H2O",
      "concentration": 1.0,
      "unit": "g",
      "extraction_method": "pdf_tabular_parsing"
    },
    {
      "name": "Wolin's vitamin solution (10x)",
      "concentration": 1.0,
      "unit": "g",
      "extraction_method": "pdf_tabular_parsing"
    }
  ],
  "preparation_instructions": "",
  "extraction_method": "pdf_text_parsing"
}