{
  "medium_id": "dsmz_461",
  "medium_name": "MINERAL MEDIUM",
  "source": "dsmz",
  "composition": [
    {
      "name": "Na2HPO4 x 2 H2O",
      "concentration": 1000.0,
      "unit": "ml",
      "extraction_method": "pdf_tabular_parsing"
    },
    {
      "name": "KH2PO4",
      "concentration": 1.45,
      "unit": "g",
      "extraction_method": "pdf_tabular_parsing"
    },
    {
      "name": "CaCl2",
      "concentration": 0.25,
      "unit": "g",
      "extraction_method": "pdf_tabular_parsing"
    },
    {
      "name": "MgSO4 x 7 H2O",
      "concentration": 0.01,
      "unit": "g",
      "extraction_method": "pdf_tabular_parsing"
    },
    {
      "name": "MnSO4",
      "concentration": 0.5,
      "unit": "g",
      "extraction_method": "pdf_tabular_parsing"
    },
    {
      "name": "NH4Cl",
      "concentration": 0.01,
      "unit": "g",
      "extraction_method": "pdf_tabular_parsing"
    },
    {
      "name": "NaCl",
      "concentration": 0.3,
      "unit": "g",
      "extraction_method": "pdf_tabular_parsing"
    },
    {
      "name": "Vitamin Solution",
      "concentration": 0.05,
      "unit": "g",
      "extraction_method": "pdf_tabular_parsing"
    },
    {
      "name": "Trace element sol. SL-10",
      "concentration": 5.0,
      "unit": "ml",
      "extraction_method": "pdf_tabular_parsing"
    }
  ],
  "preparation_instructions": "",
  "extraction_method": "pdf_text_parsing"
}