{
  "medium_id": "dsmz_1299",
  "medium_name": "Final pH: 6.5 - 7.0",
  "source": "dsmz",
  "composition": [
    {
      "name": "Final pH: 6.5 - 7.0",
      "concentration": 30.0,
      "unit": "g",
      "extraction_method": "pdf_tabular_parsing"
    },
    {
      "name": "Final volume: 1002 ml",
      "concentration": 0.1,
      "unit": "g",
      "extraction_method": "pdf_tabular_parsing"
    },
    {
      "name": "Sea Salt (SIGMA, must not show signs of caking)",
      "concentration": 1.0,
      "unit": "ml",
      "extraction_method": "pdf_tabular_parsing"
    },
    {
      "name": "Yeast extract (OXOID)",
      "concentration": 2.0,
      "unit": "g",
      "extraction_method": "pdf_tabular_parsing"
    },
    {
      "name": "Trace element solution SL-10",
      "concentration": 0.5,
      "unit": "ml",
      "extraction_method": "pdf_tabular_parsing"
    },
    {
      "name": "Trypticase peptone (BD BBL)",
      "concentration": 2.0,
      "unit": "g",
      "extraction_method": "pdf_tabular_parsing"
    },
    {
      "name": "D-Glucose",
      "concentration": 1.0,
      "unit": "ml",
      "extraction_method": "pdf_tabular_parsing"
    },
    {
      "name": "Wolin's vitamin solution (10x)",
      "concentration": 0.25,
      "unit": "g",
      "extraction_method": "pdf_tabular_parsing"
    },
    {
      "name": "Na2S x 9 H2O",
      "concentration": 1000.0,
      "unit": "ml",
      "extraction_method": "pdf_tabular_parsing"
    }
  ],
  "preparation_instructions": "",
  "extraction_method": "pdf_text_parsing"
}