{
  "medium_id": "dsmz_863",
  "medium_name": "Basal salts solution",
  "source": "dsmz",
  "composition": [
    {
      "name": "Basal salts solution",
      "concentration": 100.0,
      "unit": "ml",
      "extraction_method": "pdf_tabular_parsing"
    },
    {
      "name": "Trace elements solution",
      "concentration": 10.0,
      "unit": "ml",
      "extraction_method": "pdf_tabular_parsing"
    },
    {
      "name": "Sodium carbonate solution",
      "concentration": 24.0,
      "unit": "ml",
      "extraction_method": "pdf_tabular_parsing"
    },
    {
      "name": "Cysteine solution",
      "concentration": 5.0,
      "unit": "ml",
      "extraction_method": "pdf_tabular_parsing"
    },
    {
      "name": "Na2S solution",
      "concentration": 5.0,
      "unit": "ml",
      "extraction_method": "pdf_tabular_parsing"
    },
    {
      "name": "Degassed distilled H2O",
      "concentration": 856.0,
      "unit": "ml",
      "extraction_method": "pdf_tabular_parsing"
    }
  ],
  "preparation_instructions": "",
  "extraction_method": "pdf_text_parsing"
}