{
  "medium_id": "dsmz_309",
  "medium_name": "Medium dsmz_309",
  "source": "dsmz",
  "composition": [
    {
      "name": "Beef extract",
      "concentration": 1.5,
      "unit": "g",
      "extraction_method": "pdf_tabular_parsing"
    },
    {
      "name": "Yeast extract",
      "concentration": 3.0,
      "unit": "g",
      "extraction_method": "pdf_tabular_parsing"
    },
    {
      "name": "Peptone",
      "concentration": 6.0,
      "unit": "g",
      "extraction_method": "pdf_tabular_parsing"
    },
    {
      "name": "Glucose",
      "concentration": 1.0,
      "unit": "g",
      "extraction_method": "pdf_tabular_parsing"
    },
    {
      "name": "Casitone",
      "concentration": 4.0,
      "unit": "g",
      "extraction_method": "pdf_tabular_parsing"
    }
  ],
  "preparation_instructions": "",
  "extraction_method": "pdf_text_parsing"
}